odoo/addons/sale_commercial_partner/README.rst
odoo/addons/sale_commercial_partner/__init__.py
odoo/addons/sale_commercial_partner/__manifest__.py
odoo/addons/sale_commercial_partner/i18n/ca.po
odoo/addons/sale_commercial_partner/i18n/ca_ES.po
odoo/addons/sale_commercial_partner/i18n/de.po
odoo/addons/sale_commercial_partner/i18n/el_GR.po
odoo/addons/sale_commercial_partner/i18n/es.po
odoo/addons/sale_commercial_partner/i18n/es_MX.po
odoo/addons/sale_commercial_partner/i18n/es_VE.po
odoo/addons/sale_commercial_partner/i18n/fi.po
odoo/addons/sale_commercial_partner/i18n/fr.po
odoo/addons/sale_commercial_partner/i18n/fr_FR.po
odoo/addons/sale_commercial_partner/i18n/hr.po
odoo/addons/sale_commercial_partner/i18n/hu.po
odoo/addons/sale_commercial_partner/i18n/it.po
odoo/addons/sale_commercial_partner/i18n/nl.po
odoo/addons/sale_commercial_partner/i18n/pt.po
odoo/addons/sale_commercial_partner/i18n/pt_BR.po
odoo/addons/sale_commercial_partner/i18n/ro.po
odoo/addons/sale_commercial_partner/i18n/sale_commercial_partner.pot
odoo/addons/sale_commercial_partner/i18n/sl_SI.po
odoo/addons/sale_commercial_partner/i18n/tr.po
odoo/addons/sale_commercial_partner/i18n/vi_VN.po
odoo/addons/sale_commercial_partner/i18n/zh_CN.po
odoo/addons/sale_commercial_partner/models/__init__.py
odoo/addons/sale_commercial_partner/models/sale_order.py
odoo/addons/sale_commercial_partner/readme/CONTRIBUTORS.md
odoo/addons/sale_commercial_partner/readme/CREDITS.md
odoo/addons/sale_commercial_partner/readme/DESCRIPTION.md
odoo/addons/sale_commercial_partner/readme/USAGE.md
odoo/addons/sale_commercial_partner/static/description/icon.png
odoo/addons/sale_commercial_partner/static/description/index.html
odoo/addons/sale_commercial_partner/tests/__init__.py
odoo/addons/sale_commercial_partner/tests/test_sale_commercial_partner.py
odoo/addons/sale_commercial_partner/views/sale_order.xml
odoo/addons/sale_commercial_partner/views/sale_report.xml
odoo_addon_sale_commercial_partner-19.0.1.0.0.2.dist-info/METADATA
odoo_addon_sale_commercial_partner-19.0.1.0.0.2.dist-info/WHEEL
odoo_addon_sale_commercial_partner-19.0.1.0.0.2.dist-info/top_level.txt
odoo_addon_sale_commercial_partner-19.0.1.0.0.2.dist-info/RECORD
